{"chunk_definitions":[{"row":10,"row_count":1,"visible":true,"expansion_state":0,"options":{"engine":"r","label":"setup","include":false},"document_id":"A705B28C","chunk_id":"csetup_chunk","chunk_label":"setup"},{"row":21,"row_count":1,"visible":true,"expansion_state":0,"options":{"engine":"r","label":"loadTemps","error":true},"document_id":"A705B28C","chunk_id":"cfs5ur6b9yp1e","chunk_label":"loadTemps"},{"row":31,"row_count":1,"visible":true,"expansion_state":0,"options":{"engine":"r","label":"histTemps"},"document_id":"A705B28C","chunk_id":"clwztj6kut6pl","chunk_label":"histTemps"},{"row":44,"row_count":1,"visible":true,"expansion_state":0,"options":{"engine":"r","label":"temp_CI","error":true},"document_id":"A705B28C","chunk_id":"c4blqpu174cfo","chunk_label":"temp_CI"}],"doc_write_time":1684522075,"working_dir":null,"default_chunk_options":{"echo":true},"chunk_rendered_width":604}